<service>
	<id>athenaapi.exe</id>
	<name>Athena API</name>
	<description>Node JS Script for Athena API</description>
	<executable>C:\Program Files\nodejs\node.exe</executable>
	<argument>--harmony</argument>
	<argument>C:\Code\AthenaAPI\node_modules\node-windows\lib\wrapper.js</argument>
	<argument>--file</argument>
	<argument>C:\Code\AthenaAPI\server.js</argument>
	<argument>--scriptoptions=</argument>
	<argument>--log</argument>
	<argument>Athena API wrapper</argument>
	<argument>--grow</argument>
	<argument>0.25</argument>
	<argument>--wait</argument>
	<argument>1</argument>
	<argument>--maxrestarts</argument>
	<argument>3</argument>
	<argument>--abortonerror</argument>
	<argument>n</argument>
	<argument>--stopparentfirst</argument>
	<argument>undefined</argument>
	<logmode>rotate</logmode>
	<stoptimeout>30sec</stoptimeout>
	<serviceaccount>
		<domain>ATHENASERV001</domain>
		<user>LocalSystem</user>
		<password></password>
	</serviceaccount>
	<workingdirectory>C:\Code\AthenaAPI</workingdirectory>
</service>